[
    {
        "product_name": "HEMNES komodin, venge, 54x66 cm",
        "category": "Mobilyalar",
        "style": "Klasik",
        "color": "Venge",
        "dimensions": {
            "width_cm": 54,
            "depth_cm": 38,
            "height_cm": 66
        },
        "description": "Sürdürülebilir kaynaklardan elde edilen masif ahşaptan yapılmış komodin, geleneksel bir görünüme ve modern fonksiyona sahiptir. Sessiz, pürüzsüz çalışan çekmeceler, güne huzurlu bir başlangıç yapmanıza yardımcı olur.",
        "price": 3499,
        "image_path": "/data/products/komodinler/hemnes-venge-54x66.jpg",
        "product_link": "https://www.ikea.com.tr/urun/hemnes-venge-54x66-cm-komodin-50242619"
    },
    {
        "product_name": "RÅDMANSÖ komodin, kahverengi ceviz görünümlü, 54x38x58 cm",
        "category": "Mobilyalar",
        "style": "Modern",
        "color": "Kahverengi Ceviz Görünümü",
        "dimensions": {
            "width_cm": 54,
            "depth_cm": 38,
            "height_cm": 58
        },
        "description": "Ceviz efektli kaplama, her bir mobilya parçasına benzersiz bir karakter kazandıran, belirgin damarlı desenlere sahip, sıcak ve doğal bir görünüm yaratır. Entegre yavaş kapanma fonksiyonu sayesinde çekmece yavaş, sessiz ve yumuşak bir şekilde kapanır. Akıllı konstrüksiyonu ve üretim tekniği sayesinde fabrikada montaj süresini önemli ölçüde azaltarak hızlı ve kolay bir şekilde monte edilir.",
        "price": 3299,
        "image_path": "/data/products/komodinler/radmanso-kahverengi-ceviz.jpg",
        "product_link": "https://www.ikea.com.tr/urun/radmanso-kahverengi-ceviz-gorunum-54x38x58-cm-komodin-80593597"
    },
    {
        "product_name": "VIKHAMMER komodin, beyaz, 40x39 cm",
        "category": "Mobilyalar",
        "style": "Modern",
        "color": "Beyaz",
        "dimensions": {
            "width_cm": 40,
            "depth_cm": 39,
            "height_cm": 65
        },
        "description": "Yumuşak kapanan çekmece sayesinde huzurlu bir sabaha uyanın. Temiz hatları ve sade tasarımıyla yatağınızın yanında harika duran komodinin üstündeki rafa kitaplarınızı koyabilirsiniz.",
        "price": 3699,
        "image_path": "/data/products/komodinler/vikhammer-beyaz.jpg",
        "product_link": "https://www.ikea.com.tr/urun/vikhammer-beyaz-40x39-cm-komodin-00381764"
    },
    {
        "product_name": "MALM 2 çekmeceli şifonyer/komodin, venge, 40x55 cm",
        "category": "Mobilyalar",
        "style": "Modern",
        "color": "Venge",
        "dimensions": {
            "width_cm": 40,
            "depth_cm": 48,
            "height_cm": 55
        },
        "description": "Eviniz güvenli bir yer olmalıdır. Bu nedenle şifonyerin duvara sabitlenmesi için güvenlik aparatı ürüne dahildir. Sade görünümü sayesinde yatak odanıza veya misafir odanıza kolayca uyum sağlar. Pürüzsüz çekmeceler ve farklı cila seçenekleri ile MALM serisindeki diğer mobilyalarla kombine edebilirsiniz.",
        "price": 2199,
        "image_path": "/data/products/komodinler/malm-venge.jpg",
        "product_link": "https://www.ikea.com.tr/urun/malm-venge-40x55-cm-komodin-00103343"
    },
    {
        "product_name": "HEMNES 2 çekmeceli şifonyer/komodin, venge, 46x35 cm",
        "category": "Mobilyalar",
        "style": "Klasik",
        "color": "Venge",
        "dimensions": {
            "width_cm": 46,
            "depth_cm": 35,
            "height_cm": 70
        },
        "description": "Eviniz elbette tüm aile için güvenli bir yer olmalıdır. Bu nedenle şifonyeri duvara sabitlemenizi sağlayan güvenlik bağlantı parçaları ürüne dahildir. Sürdürülebilir kaynaklardan elde edilen masif ahşaptan yapılmıştır. Kolay açılan stoperli çekmecelere sahiptir.",
        "price": 2799,
        "image_path": "/data/products/komodinler/hemnes-venge-46x35.jpg",
        "product_link": "https://www.ikea.com.tr/urun/hemnes-venge-46x35x70-cm-komodin-90121234"
    }
]